micropython_qr.py
micropython_qr-0.0.1.dist-info/METADATA
micropython_qr-0.0.1.dist-info/WHEEL
micropython_qr-0.0.1.dist-info/licenses/LICENSE
micropython_qr-0.0.1.dist-info/RECORD
